sphinx_pyreverse/__init__.py
sphinx_pyreverse/uml_generate_directive.py
sphinx_pyreverse-0.0.18.dist-info/LICENSE
sphinx_pyreverse-0.0.18.dist-info/METADATA
sphinx_pyreverse-0.0.18.dist-info/WHEEL
sphinx_pyreverse-0.0.18.dist-info/top_level.txt
sphinx_pyreverse-0.0.18.dist-info/RECORD
