Metadata-Version: 2.1
Name: sphinx-pyreverse
Version: 0.0.18
Summary: A simple sphinx extension to generate UML diagrams with pyreverse
Home-page: https://github.com/alendit/sphinx-pyreverse
Author: Dimitri Vorona
Author-email: vorona@in.tum.de
License: GPLv3
Keywords: sphinx extension uml pyreverse
Classifier: Development Status :: 2 - Pre-Alpha
Classifier: Intended Audience :: Information Technology
Classifier: License :: OSI Approved :: GNU General Public License v3 or later (GPLv3+)
Classifier: Operating System :: Microsoft :: Windows
Classifier: Operating System :: POSIX
Classifier: Programming Language :: Python
Classifier: Programming Language :: Python :: 3
Classifier: Programming Language :: Python :: 3.4
Classifier: Topic :: Utilities
License-File: LICENSE
Requires-Dist: astroid (>=2.5.7)
Requires-Dist: docutils
Requires-Dist: pylint
Requires-Dist: sphinx
Provides-Extra: deploy
Requires-Dist: twine ; extra == 'deploy'
Provides-Extra: pil
Requires-Dist: pillow ; extra == 'pil'
Provides-Extra: tests
Requires-Dist: black (==21.6b0) ; extra == 'tests'
Requires-Dist: docutils ; extra == 'tests'
Requires-Dist: flake8 ; extra == 'tests'
Requires-Dist: isort (==5.8.0) ; extra == 'tests'
Requires-Dist: pytest ; extra == 'tests'
Requires-Dist: pytest-cov ; extra == 'tests'
Requires-Dist: sphinx (==4.5.0) ; extra == 'tests'
